awslabs/__init__.py
awslabs/rds_control_plane_mcp_server/__init__.py
awslabs/rds_control_plane_mcp_server/main.py
awslabs/rds_control_plane_mcp_server/common/__init__.py
awslabs/rds_control_plane_mcp_server/common/connection.py
awslabs/rds_control_plane_mcp_server/common/constants.py
awslabs/rds_control_plane_mcp_server/common/context.py
awslabs/rds_control_plane_mcp_server/common/server.py
awslabs/rds_control_plane_mcp_server/common/utils.py
awslabs/rds_control_plane_mcp_server/common/decorators/handle_exceptions.py
awslabs/rds_control_plane_mcp_server/common/decorators/readonly_check.py
awslabs/rds_control_plane_mcp_server/common/decorators/require_confirmation.py
awslabs/rds_control_plane_mcp_server/resources/__init__.py
awslabs/rds_control_plane_mcp_server/resources/db_cluster/__init__.py
awslabs/rds_control_plane_mcp_server/resources/db_cluster/describe_cluster_detail.py
awslabs/rds_control_plane_mcp_server/resources/db_cluster/list_clusters.py
awslabs/rds_control_plane_mcp_server/resources/db_instance/__init__.py
awslabs/rds_control_plane_mcp_server/resources/db_instance/describe_instance_detail.py
awslabs/rds_control_plane_mcp_server/resources/db_instance/list_db_logs.py
awslabs/rds_control_plane_mcp_server/resources/db_instance/list_instances.py
awslabs/rds_control_plane_mcp_server/resources/db_instance/list_performance_reports.py
awslabs/rds_control_plane_mcp_server/resources/db_instance/read_performance_report.py
awslabs/rds_control_plane_mcp_server/resources/general/__init__.py
awslabs/rds_control_plane_mcp_server/resources/general/list_metrics.py
awslabs/rds_control_plane_mcp_server/tools/__init__.py
awslabs/rds_control_plane_mcp_server/tools/db_cluster/__init__.py
awslabs/rds_control_plane_mcp_server/tools/db_cluster/change_cluster_status.py
awslabs/rds_control_plane_mcp_server/tools/db_cluster/create_cluster.py
awslabs/rds_control_plane_mcp_server/tools/db_cluster/delete_cluster.py
datgfg_rds_control_plane_mcp_server-0.0.1.dist-info/METADATA
datgfg_rds_control_plane_mcp_server-0.0.1.dist-info/WHEEL
datgfg_rds_control_plane_mcp_server-0.0.1.dist-info/entry_points.txt
datgfg_rds_control_plane_mcp_server-0.0.1.dist-info/licenses/LICENSE
datgfg_rds_control_plane_mcp_server-0.0.1.dist-info/licenses/NOTICE
datgfg_rds_control_plane_mcp_server-0.0.1.dist-info/RECORD
