Metadata-Version: 2.4
Name: datgfg.rds-control-plane-mcp-server
Version: 0.0.1
Summary: An AWS Labs Model Context Protocol (MCP) server for rds-control-plane
Project-URL: homepage, https://awslabs.github.io/mcp/
Project-URL: docs, https://awslabs.github.io/mcp/servers/rds-control-plane-mcp-server/
Project-URL: documentation, https://awslabs.github.io/mcp/servers/rds-control-plane-mcp-server/
Project-URL: repository, https://github.com/awslabs/mcp.git
Project-URL: changelog, https://github.com/awslabs/mcp/blob/main/src/rds-control-plane-mcp-server/CHANGELOG.md
Author: Amazon Web Services
Author-email: AWSLabs MCP <203918161+awslabs-mcp@users.noreply.github.com>, Jonathan Manuel <jonathan.imanuel@gmail.com>, Grace Lee <jaeeungracelee@gmail.com>, Runzhuo Li <runzhuo1990@gmail.com>
License: Apache-2.0
License-File: LICENSE
License-File: NOTICE
Classifier: License :: OSI Approved :: Apache Software License
Classifier: Operating System :: OS Independent
Classifier: Programming Language :: Python
Classifier: Programming Language :: Python :: 3
Classifier: Programming Language :: Python :: 3.10
Classifier: Programming Language :: Python :: 3.11
Classifier: Programming Language :: Python :: 3.12
Classifier: Programming Language :: Python :: 3.13
Requires-Python: >=3.10
Requires-Dist: boto3>=1.38.40
Requires-Dist: loguru>=0.7.0
Requires-Dist: mcp[cli]>=1.6.0
Requires-Dist: mypy-boto3-cloudwatch>=1.39.0
Requires-Dist: mypy-boto3-rds>=1.38.0
Requires-Dist: mypy-boto3>=1.39.0
Requires-Dist: pydantic>=2.10.6
